apimarket/__init__.py
apimarket/api_market_client.py
apimarket/cli.py
apimarket/kiota-lock.json
apimarket/validations.py
apimarket/api/api_request_builder.py
apimarket/api/ai/ai_request_builder.py
apimarket/api/ai/grupo/grupo_request_builder.py
apimarket/api/ai/grupo/procesamiento_masivo/procesamiento_masivo400_error.py
apimarket/api/ai/grupo/procesamiento_masivo/procesamiento_masivo401_error.py
apimarket/api/ai/grupo/procesamiento_masivo/procesamiento_masivo4_x_x_error.py
apimarket/api/ai/grupo/procesamiento_masivo/procesamiento_masivo5_x_x_error.py
apimarket/api/ai/grupo/procesamiento_masivo/procesamiento_masivo_post_request_body.py
apimarket/api/ai/grupo/procesamiento_masivo/procesamiento_masivo_request_builder.py
apimarket/api/ai/v2/v2_request_builder.py
apimarket/api/ai/v2/kie/kie400_error.py
apimarket/api/ai/v2/kie/kie401_error.py
apimarket/api/ai/v2/kie/kie4_x_x_error.py
apimarket/api/ai/v2/kie/kie5_x_x_error.py
apimarket/api/ai/v2/kie/kie_post_request_body.py
apimarket/api/ai/v2/kie/kie_request_builder.py
apimarket/api/ai/v2/mrz/mrz400_error.py
apimarket/api/ai/v2/mrz/mrz401_error.py
apimarket/api/ai/v2/mrz/mrz4_x_x_error.py
apimarket/api/ai/v2/mrz/mrz5_x_x_error.py
apimarket/api/ai/v2/mrz/mrz_post_request_body.py
apimarket/api/ai/v2/mrz/mrz_post_response.py
apimarket/api/ai/v2/mrz/mrz_request_builder.py
apimarket/api/ai/v2/templates/templates400_error.py
apimarket/api/ai/v2/templates/templates401_error.py
apimarket/api/ai/v2/templates/templates4_x_x_error.py
apimarket/api/ai/v2/templates/templates500_error.py
apimarket/api/ai/v2/templates/templates5_x_x_error.py
apimarket/api/ai/v2/templates/templates_post_response.py
apimarket/api/ai/v2/templates/templates_put_response.py
apimarket/api/ai/v2/templates/templates_request_builder.py
apimarket/api/ai/v2/universal_ocr/universal_ocr400_error.py
apimarket/api/ai/v2/universal_ocr/universal_ocr401_error.py
apimarket/api/ai/v2/universal_ocr/universal_ocr4_x_x_error.py
apimarket-3.3.1.dist-info/LICENSE.txt
apimarket-3.3.1.dist-info/METADATA
apimarket-3.3.1.dist-info/WHEEL
apimarket-3.3.1.dist-info/entry_points.txt
apimarket-3.3.1.dist-info/top_level.txt
apimarket-3.3.1.dist-info/RECORD
