Metadata-Version: 2.2
Name: apimarket
Version: 3.3.1
Summary: API Market SDK for Python Development
Home-page: https://apimarket.mx/
Author: Carlos Eduardo Sanchez Torres (sanchezcarlosjr)
Author-email: soporte@apimarket.mx
License: MIT
Project-URL: Documentation, https://github.com/api-market-company/apimarket-sdk-python
Platform: any
Classifier: Development Status :: 5 - Production/Stable
Classifier: Topic :: Utilities
Classifier: Programming Language :: Python
Classifier: Programming Language :: Python :: 3
Classifier: Environment :: Console
Classifier: Intended Audience :: Developers
Classifier: License :: OSI Approved :: MIT License
Classifier: Operating System :: POSIX :: Linux
Classifier: Operating System :: Unix
Classifier: Operating System :: MacOS
Classifier: Operating System :: Microsoft :: Windows
License-File: LICENSE.txt
Requires-Dist: importlib-metadata; python_version < "3.8"
Requires-Dist: python-decouple==3.8
Requires-Dist: httpx[http2]==0.27.0
Requires-Dist: kink==0.8.0
Requires-Dist: dateparser==1.2.0
Requires-Dist: microsoft-kiota-serialization-json==1.2.0
Requires-Dist: microsoft-kiota-serialization-text==1.0.0
Requires-Dist: microsoft-kiota-serialization-form==0.1.0
Requires-Dist: microsoft-kiota-serialization-multipart==0.1.0
Requires-Dist: microsoft-kiota-http==1.3.1
Requires-Dist: urllib3==2.2.1
Requires-Dist: nest_asyncio==1.6.0
Requires-Dist: microsoft-kiota-abstractions==1.3.3
Provides-Extra: testing
Requires-Dist: setuptools; extra == "testing"
Requires-Dist: pytest; extra == "testing"
Requires-Dist: pytest-cov; extra == "testing"
